setup.py
blockstack_utxo/__init__.py
blockstack_utxo/blockstack_utxo.py
blockstack_utxo/utxo.py
blockstack_utxo/version.py
blockstack_utxo.egg-info/PKG-INFO
blockstack_utxo.egg-info/SOURCES.txt
blockstack_utxo.egg-info/dependency_links.txt
blockstack_utxo.egg-info/not-zip-safe
blockstack_utxo.egg-info/requires.txt
blockstack_utxo.egg-info/top_level.txt