Metadata-Version: 1.1
Name: blockstack-utxo
Version: 0.0.1.1
Summary: Python library for interacting with various UTXO providers
Home-page: https://github.com/blockstack/blockstack-utxo
Author: Blockstack.org
Author-email: support@blockstack.org
License: MIT
Download-URL: https://github.com/blockstack/blockstack-utxo/archive/master.zip
Keywords: blockchain bitcoin btc cryptocurrency name key value store data
Platform: UNKNOWN
Classifier: Intended Audience :: Developers
Classifier: License :: OSI Approved :: GNU General Public License v3 (GPLv3)
Classifier: Operating System :: OS Independent
Classifier: Programming Language :: Python
Classifier: Topic :: Internet
Classifier: Topic :: Security :: Cryptography
Classifier: Topic :: Software Development :: Libraries :: Python Modules
